pywincolor/__init__.py
pywincolor/pywincolor.py
pywincolor-5.18.2024.dist-info/METADATA
pywincolor-5.18.2024.dist-info/WHEEL
pywincolor-5.18.2024.dist-info/top_level.txt
pywincolor-5.18.2024.dist-info/RECORD
